agentverse_client/__init__.py
agentverse_client/aio_almanac_README.md
agentverse_client/aio_search_README.md
agentverse_client/almanac/__init__.py
agentverse_client/almanac/aio/__init__.py
agentverse_client/almanac/aio/api/__init__.py
agentverse_client/almanac/aio/api/almanac_api.py
agentverse_client/almanac/aio/api_client.py
agentverse_client/almanac/aio/api_response.py
agentverse_client/almanac/aio/configuration.py
agentverse_client/almanac/aio/docs/AddressPrefix.md
agentverse_client/almanac/aio/docs/Agent.md
agentverse_client/almanac/aio/docs/AgentEndpoint.md
agentverse_client/almanac/aio/docs/AgentNameAvailability.md
agentverse_client/almanac/aio/docs/AgentNameAvailabilityStatus.md
agentverse_client/almanac/aio/docs/AgentRecord.md
agentverse_client/almanac/aio/docs/AgentRegistrationAttestation.md
agentverse_client/almanac/aio/docs/AgentRegistrationAttestationBatch.md
agentverse_client/almanac/aio/docs/AgentRegistrationAttestationMetadataValue.md
agentverse_client/almanac/aio/docs/AgentStatus.md
agentverse_client/almanac/aio/docs/AgentStatusUpdate.md
agentverse_client/almanac/aio/docs/AgentType.md
agentverse_client/almanac/aio/docs/AlmanacApi.md
agentverse_client/almanac/aio/docs/DeveloperCategory.md
agentverse_client/almanac/aio/docs/DomainRecord.md
agentverse_client/almanac/aio/docs/EndpointInput.md
agentverse_client/almanac/aio/docs/EndpointOutput.md
agentverse_client/almanac/aio/docs/HTTPValidationError.md
agentverse_client/almanac/aio/docs/Interaction.md
agentverse_client/almanac/aio/docs/InteractionType.md
agentverse_client/almanac/aio/docs/LocationInner.md
agentverse_client/almanac/aio/docs/Manifest.md
agentverse_client/almanac/aio/docs/Metadata.md
agentverse_client/almanac/aio/docs/Model.md
agentverse_client/almanac/aio/docs/ResolvedProtocolDigest.md
agentverse_client/almanac/aio/docs/ServiceRecord.md
agentverse_client/almanac/aio/docs/ValidationError.md
agentverse_client/almanac/aio/exceptions.py
agentverse_client/almanac/aio/models/__init__.py
agentverse_client-0.1.9.dist-info/METADATA
agentverse_client-0.1.9.dist-info/WHEEL
agentverse_client-0.1.9.dist-info/RECORD
